LICENSE
MANIFEST.in
README.md
pyproject.toml
setup.py
src/clusterondemand/__init__.py
src/clusterondemand/accept_eula.py
src/clusterondemand/bcm_version.py
src/clusterondemand/brightsetup.py
src/clusterondemand/cidr.py
src/clusterondemand/cli.py
src/clusterondemand/clustercreate.py
src/clusterondemand/clusternameprefix.py
src/clusterondemand/cmclient.py
src/clusterondemand/command_runner.py
src/clusterondemand/configdump.py
src/clusterondemand/configshow.py
src/clusterondemand/configuration.py
src/clusterondemand/configuration_validation.py
src/clusterondemand/const.py
src/clusterondemand/contextmanagers.py
src/clusterondemand/copyfile.py
src/clusterondemand/decorators.py
src/clusterondemand/eula.txt
src/clusterondemand/exceptions.py
src/clusterondemand/findclusters.py
src/clusterondemand/imagemanifest.py
src/clusterondemand/imagerepo.py
src/clusterondemand/imagetable.py
src/clusterondemand/import_utils.py
src/clusterondemand/inbound_traffic_rule.py
src/clusterondemand/ip.py
src/clusterondemand/localpath.py
src/clusterondemand/node_definition.py
src/clusterondemand/paramvalidation.py
src/clusterondemand/py.typed
src/clusterondemand/reporting_reader.py
src/clusterondemand/setup_logging.py
src/clusterondemand/ssh.py
src/clusterondemand/ssh_key.py
src/clusterondemand/summary.py
src/clusterondemand/tabcompletion_generate.py
src/clusterondemand/tags.py
src/clusterondemand/testutils.py
src/clusterondemand/text.py
src/clusterondemand/tracing.py
src/clusterondemand/utils.py
src/clusterondemand/version.py
src/clusterondemand/versioned_product_key.py
src/clusterondemand/vlan.py
src/clusterondemand/wait_helpers.py
src/clusterondemand/cloudconfig/__init__.py
src/clusterondemand/cloudconfig/cloudconfig.py
src/clusterondemand/cloudconfig/headcommands.py
src/clusterondemand/cloudconfig/headfiles.py
src/clusterondemand/codoutput/__init__.py
src/clusterondemand/codoutput/datetimefunctions.py
src/clusterondemand/codoutput/sortingutils.py
src/clusterondemand/images/__init__.py
src/cm_cluster_on_demand.egg-info/PKG-INFO
src/cm_cluster_on_demand.egg-info/SOURCES.txt
src/cm_cluster_on_demand.egg-info/dependency_links.txt
src/cm_cluster_on_demand.egg-info/entry_points.txt
src/cm_cluster_on_demand.egg-info/requires.txt
src/cm_cluster_on_demand.egg-info/top_level.txt
