Metadata-Version: 2.4
Name: cm-cluster-on-demand
Version: 11.0.5
Summary: NVIDIA Base Command Manager Cluster on Demand
Author-email: Base Command Manager Cloud Team <sw-bright-cloud-team@nvidia.onmicrosoft.com>
License-Expression: Apache-2.0
Project-URL: Documentation, https://docs.nvidia.com/base-command-manager/
Classifier: Development Status :: 5 - Production/Stable
Classifier: Intended Audience :: Information Technology
Classifier: Intended Audience :: Science/Research
Classifier: Intended Audience :: System Administrators
Classifier: Programming Language :: Python :: 3 :: Only
Classifier: Programming Language :: Python :: 3.12
Classifier: Topic :: System :: Clustering
Classifier: Topic :: System :: Installation/Setup
Classifier: Topic :: System :: Monitoring
Classifier: Topic :: System :: Systems Administration
Requires-Python: >=3.12
License-File: LICENSE
Requires-Dist: cm-cluster-on-demand-config==11.0.5
Requires-Dist: filelock>=2.0.8
Requires-Dist: netaddr>=0.8.0
Requires-Dist: passlib>=1.7.4
Requires-Dist: PrettyTable>=3.4.0
Requires-Dist: python_dateutil>=1.5
Requires-Dist: pytz>=2022.5
Requires-Dist: pyyaml>=6.0
Requires-Dist: requests>=2.31.0
Requires-Dist: rich>=13.7.0
Requires-Dist: tenacity>=8.1.0
Requires-Dist: urllib3>=2.5.0
Dynamic: license-file
Dynamic: requires-dist
